{
	"update_id": "d1ec51fd-337e-4d7d-a670-24d84092b6dd",
	"title": "2023-03 Cumulative Update for Microsoft server operating system, version 22H2 for x64-based Systems (KB5023705)",
	"description": "Install this update to resolve issues in Windows. For a complete listing of the issues that are included in this update, see the associated Microsoft Knowledge Base article for more information. After you install this item, you may have to restart your computer.",
	"architecture": "AMD64",
	"classification": "SecurityUpdates",
	"supported_products": "MicrosoftServerOperatingSystem-22H2",
	"supported_languages": "all",
	"security_bulliten": "n/a",
	"msrc_severity": "Critical",
	"kb_article": "5023705",
	"more_info": "https://support.microsoft.com/help/5023705",
	"support_url": "https://support.microsoft.com/help/5023705",
	"supersededby": [
		{
			"title": "2023-08 Cumulative Update for Microsoft server operating system, version 22H2 for x64-based Systems (KB5029250)",
			"update_id": "36a4b6e1-3c98-4d7a-85d6-b92e434a6990"
		},
		{
			"title": "2024-04 Cumulative Update for Microsoft server operating system, version 22H2 for x64-based Systems (KB5036909)",
			"update_id": "5e8f249e-e228-42fc-a10b-54a257aa1ec5"
		},
		{
			"title": "2023-12 Cumulative Update for Microsoft server operating system, version 22H2 for x64-based Systems (KB5033118)",
			"update_id": "5200c9a6-2104-4c06-b2a6-e061ba2dee56"
		},
		{
			"title": "2024-02 Cumulative Update for Microsoft server operating system, version 22H2 for x64-based Systems (KB5034770)",
			"update_id": "30ef48af-9a3f-46da-adfa-84cdb29cc020"
		},
		{
			"title": "2023-07 Cumulative Update for Microsoft server operating system, version 22H2 for x64-based Systems (KB5028171)",
			"update_id": "a0d22f4d-9ebd-414b-91e4-d93fd8d901c7"
		},
		{
			"title": "2024-03 Cumulative Update for Microsoft server operating system, version 22H2 for x64-based Systems (KB5035857)",
			"update_id": "a7dad4d4-48b1-41e2-89e7-004e046c053b"
		},
		{
			"title": "2023-05 Cumulative Update for Microsoft server operating system, version 22H2 for x64-based Systems (KB5026370)",
			"update_id": "98642411-e874-45e4-8603-2d499b695e77"
		},
		{
			"title": "2023-11 Cumulative Update for Microsoft server operating system, version 22H2 for x64-based Systems (KB5032198)",
			"update_id": "4e346ce8-fecb-4e88-96ea-db3603fa0ef2"
		},
		{
			"title": "2023-04 Cumulative Update for Microsoft server operating system, version 22H2 for x64-based Systems (KB5025230)",
			"update_id": "c990128c-17ca-4a56-8494-be037672716c"
		},
		{
			"title": "2023-06 Cumulative Update for Microsoft server operating system, version 22H2 for x64-based Systems (KB5027225)",
			"update_id": "ac02bcf4-be2b-4a80-a2c4-dd867f6e51e2"
		},
		{
			"title": "2023-09 Cumulative Update for Microsoft server operating system, version 22H2 for x64-based Systems (KB5030216)",
			"update_id": "ed85c4d7-14b5-4eba-a505-42cf24bab517"
		},
		{
			"title": "2023-10 Cumulative Update for Microsoft server operating system, version 22H2 for x64-based Systems (KB5031364)",
			"update_id": "b49dd552-b7c2-44c7-9117-c4867f42ad97"
		},
		{
			"title": "2024-01 Cumulative Update for Microsoft server operating system, version 22H2 for x64-based Systems (KB5034129)",
			"update_id": "d702b246-9d3c-4925-80f0-3b091f08972b"
		}
	],
	"supersedes": [
		"2022-10 Cumulative Update Preview for Microsoft server operating system, version 22H2 for x64-based Systems (KB5018485)",
		"2023-02 Cumulative Update for Microsoft server operating system, version 22H2 for x64-based Systems (KB5022842)",
		"2022-10 Cumulative Update for Microsoft server operating system, version 22H2 for x64-based Systems (KB5020436)",
		"2022-11 Cumulative Update for Microsoft server operating system, version 22H2 for x64-based Systems (KB5019081)",
		"2022-11 Cumulative Update Preview for Microsoft server operating system, version 22H2 for x64-based Systems (KB5020032)",
		"2022-11 Cumulative Update for Microsoft server operating system, version 22H2 for x64-based Systems (KB5021656)",
		"2023-01 Cumulative Update for Microsoft server operating system, version 22H2 for x64-based Systems (KB5022291)",
		"2022-10 Cumulative Update for Microsoft server operating system, version 22H2 for x64-based Systems (KB5018421)",
		"2022-12 Cumulative Update for Microsoft server operating system, version 22H2 for x64-based Systems (KB5021249)"
	],
	"reboot_behavior": "Can request restart",
	"user_input": "No",
	"connectivity": "No",
	"uninstall_notes": "ThissoftwareupdatecanberemovedbyselectingViewinstalledupdatesintheProgramsandFeaturesControlPanel.",
	"uninstall_steps": "n/a",
	"last_modified": "3/14/2023"
}
